alt_cinder_sch/__init__.py
alt_cinder_sch/host_managers.py
alt_cinder_sch/scheduler_drivers.py
alt_cinder_sch/filters/__init__.py
alt_cinder_sch/filters/capacity_filter.py
alt_cinder_sch-0.1.1.dist-info/DESCRIPTION.rst
alt_cinder_sch-0.1.1.dist-info/METADATA
alt_cinder_sch-0.1.1.dist-info/RECORD
alt_cinder_sch-0.1.1.dist-info/WHEEL
alt_cinder_sch-0.1.1.dist-info/entry_points.txt
alt_cinder_sch-0.1.1.dist-info/metadata.json
alt_cinder_sch-0.1.1.dist-info/top_level.txt
