Metadata-Version: 2.0
Name: alt-cinder-sch
Version: 0.1.1
Summary: Alternative Classes -filter, host manager, etc.- for OpenStack's Cinder
Home-page: https://github.com/akrog/alt_cinder_sch
Author: Gorka Eguileor
Author-email: gorka@eguileor.com
License: Apache Software License 2.0
Keywords: OpenStack Cinder scheduler filter
Platform: UNKNOWN
Classifier: Development Status :: 2 - Pre-Alpha
Classifier: Intended Audience :: System Administrators
Classifier: License :: OSI Approved :: Apache Software License
Classifier: Natural Language :: English
Classifier: Programming Language :: Python :: 2
Classifier: Programming Language :: Python :: 2.6
Classifier: Programming Language :: Python :: 2.7
Classifier: Programming Language :: Python :: 3
Classifier: Programming Language :: Python :: 3.3
Classifier: Programming Language :: Python :: 3.4
Classifier: Programming Language :: Python :: 3.5
Requires-Dist: cinder
